shipyard_databricks_sql/__init__.py
shipyard_databricks_sql/cli/__init__.py
shipyard_databricks_sql/cli/authtest.py
shipyard_databricks_sql/cli/copy_from_s3.py
shipyard_databricks_sql/cli/execute.py
shipyard_databricks_sql/cli/fetch.py
shipyard_databricks_sql/cli/upload.py
shipyard_databricks_sql/databricks.py
shipyard_databricks_sql/utils/exceptions.py
shipyard_databricks_sql/utils/utils.py
shipyard_databricks_sql-0.2.0.dist-info/METADATA
shipyard_databricks_sql-0.2.0.dist-info/WHEEL
shipyard_databricks_sql-0.2.0.dist-info/RECORD
