Metadata-Version: 2.1
Name: shipyard-databricks-sql
Version: 0.2.0
Summary: A local client for connecting and working Databricks SQL Warehouses
Author: wrp801
Author-email: wespoulsen@gmail.com
Requires-Python: >=3.9,<4.0
Classifier: Programming Language :: Python :: 3
Classifier: Programming Language :: Python :: 3.9
Classifier: Programming Language :: Python :: 3.10
Classifier: Programming Language :: Python :: 3.11
Requires-Dist: databricks-sdk (>=0.16.0,<0.17.0)
Requires-Dist: databricks-sql-connector (>=3.1.0,<4.0.0)
Requires-Dist: pandas (>=2.0,<3.0)
Requires-Dist: shipyard-bp-utils (>=1.1.0,<2.0.0)
Requires-Dist: shipyard-templates (>=0.6.2,<0.7.0)
